[
  {
    "id": 1,
    "name": "Carlos Rodriguez",
    "email": "carlos.rodriguez@email.com",
    "phone": "+34 612 345 678"
  },
  {
    "id": 2,
    "name": "Ana Martinez",
    "email": "ana.martinez@email.com",
    "phone": "+34 623 456 789"
  },
  {
    "id": 3,
    "name": "Miguel Sanchez",
    "email": "miguel.sanchez@email.com",
    "phone": "+34 634 567 890"
  },
  {
    "id": 4,
    "name": "Laura Fernandez",
    "email": "laura.fernandez@email.com",
    "phone": "+34 645 678 901"
  },
  {
    "id": 5,
    "name": "Pablo Moreno",
    "email": "pablo.moreno@email.com",
    "phone": "+34 656 789 012"
  },
  {
    "id": 6,
    "name": "Isabel Garcia",
    "email": "isabel.garcia@email.com",
    "phone": "+34 667 890 123"
  },
  {
    "id": 7,
    "name": "David Lopez",
    "email": "david.lopez@email.com",
    "phone": "+34 678 901 234"
  },
  {
    "id": 8,
    "name": "Carmen Ruiz",
    "email": "carmen.ruiz@email.com",
    "phone": "+34 689 012 345"
  },
  {
    "id": 9,
    "name": "Jorge Navarro",
    "email": "jorge.navarro@email.com",
    "phone": "+34 690 123 456"
  },
  {
    "id": 10,
    "name": "Elena Torres",
    "email": "elena.torres@email.com",
    "phone": "+34 701 234 567"
  },
  {
    "id": 11,
    "name": "Antonio Jimenez",
    "email": "antonio.jimenez@email.com",
    "phone": "+34 712 345 678"
  },
  {
    "id": 12,
    "name": "Maria Romero",
    "email": "maria.romero@email.com",
    "phone": "+34 723 456 789"
  },
  {
    "id": 13,
    "name": "Francisco Serrano",
    "email": "francisco.serrano@email.com",
    "phone": "+34 734 567 890"
  },
  {
    "id": 14,
    "name": "Lucia Ortiz",
    "email": "lucia.ortiz@email.com",
    "phone": "+34 745 678 901"
  },
  {
    "id": 15,
    "name": "Roberto Molina",
    "email": "roberto.molina@email.com",
    "phone": "+34 756 789 012"
  }
]
